{
    "Achieve Your First Level 10": {},
    "Achieve Your First Level 20": {},
    "Achieve Your First Level 5": {},
    "Achieve Your First Level Up": {},
    "Build a Room in Your Player Owned House": {},
    "Burn Some Coloured Logs": {},
    "Burn Some Food": {},
    "Burn Some Normal Logs": {},
    "Burn Some Oak Logs": {
        "Skill1": "Firemaking",
        "Level1": "15"
    },
    "Bury Some Bones": {},
    "Cast Home Teleport": {},
    "Catch a Baby Impling": {
        "Skill1": "Hunter",
        "Level1": "17"
    },
    "Catch a Herring": {
        "Skill1": "Fishing",
        "Level1": "10"
    },
    "Catch a Shrimp": {},
    "Catch an Anchovy": {
        "Skill1": "Fishing",
        "Level1": "15"
    },
    "Check Your Slayer Task": {},
    "Chop Some Logs": {},
    "Chop Some Logs With a Steel Axe": {
        "Skill1": "Woodcutting",
        "Level1": "6"
    },
    "Clean a Grimy Guam": {
        "Skill1": "Herblore",
        "Level1": "3"
    },
    "Complete a Beginner Clue Scroll": {},
    "Complete a Rooftop Agility Course": {
        "Skill1": "Agility",
        "Level1": "10"
    },
    "Complete an Easy Clue Scroll": {},
    "Complete the Easy Western Provinces Diary": {
        "Notes": "See diary page"
    },
    "Complete the Leagues Tutorial": {},
    "Cook a Shrimp": {},
    "Craft a Leather Body": {
        "Skill1": "Crafting",
        "Level1": "14"
    },
    "Craft Any Rune": {},
    "Cut a Sapphire": {
        "Skill1": "Crafting",
        "Level1": "20"
    },
    "Defeat a Goblin": {},
    "Defeat a Guard": {},
    "Defeat a Moss Giant": {},
    "Drink a Strength Potion": {},
    "Earn Some Slayer Points": {
        "Skill1": "Combat",
        "Level1": "20"
    },
    "Eat some Purple Sweets": {},
    "Enter your Player Owned House": {},
    "Equip a Full Mithril Set": {
        "Skill1": "Defence",
        "Level1": "20"
    },
    "Equip a Maple Shortbow": {
        "Skill1": "Ranged",
        "Level1": "30"
    },
    "Equip a Mithril Weapon": {
        "Skill1": "Attack",
        "Level1": "20"
    },
    "Equip a Spiny Helmet": {
        "Skill1": "Defence",
        "Level1": "5"
    },
    "Equip a Studded Body and Chaps": {
        "Skill1": "Ranged",
        "Level1": "20",
        "Skill2": "Defence",
        "Level2": "20"
    },
    "Equip a Wizard Robe and Hat": {},
    "Equip an Elemental Staff": {},
    "Fletch 150 Iron Arrows": {
        "Skill1": "Fletching",
        "Level1": "15"
    },
    "Fletch an Oak Shortbow": {
        "Skill1": "Fletching",
        "Level1": "20"
    },
    "Fletch Some Arrow Shafts": {},
    "Gain a Unique Item From a Beginner Clue": {},
    "Gain a Unique Item From an Easy Clue": {},
    "Light a Torch": {},
    "Locate a Runecrafting Altar With a Talisman": {},
    "Make an Attack Potion": {
        "Skill1": "Herblore",
        "Level1": "3"
    },
    "Mine some Copper Ore": {},
    "Mine some Ore With a Steel Pickaxe": {
        "Skill1": "Mining",
        "Level1": "6"
    },
    "Obtain a Bird Nest": {},
    "Obtain a Gem While Mining": {},
    "Obtain a Mark of Grace": {
        "Skill1": "Agility",
        "Level1": "10"
    },
    "Open 28 Coin Pouches At Once": {},
    "Open the Leagues Menu": {},
    "Pickpocket a Citizen": {},
    "Plant Seeds in an Allotment Patch": {},
    "Protect Your Crops": {},
    "Purchase a Player Owned House": {},
    "Rake a Farming Patch": {},
    "Reach Base Level 10": {},
    "Reach Base Level 20": {},
    "Reach Base Level 5": {},
    "Reach Combat Level 10": {},
    "Reach Combat Level 25": {},
    "Reach Total Level 100": {},
    "Reach Total Level 250": {},
    "Reach Total Level 500": {},
    "Receive a Slayer Task": {},
    "Restore 5 Prayer Points at an Altar": {
        "Skill1": "Prayer",
        "Level1": "5"
    },
    "Smelt a Bronze Bar": {},
    "Smelt an Iron Bar": {
        "Skill1": "Smithing",
        "Level1": "15"
    },
    "Smith 150 Iron Arrowtips": {
        "Skill1": "Smithing",
        "Level1": "20"
    },
    "Snare a Bird": {},
    "Spin a Ball of Wool": {},
    "Steal a Chocolate Slice": {
        "Skill1": "Thieving",
        "Level1": "5"
    },
    "Successfully Cook 5 Pieces of Food": {},
    "Superhuman Strength and Improved Reflexes": {
        "Skill1": "Prayer",
        "Level1": "16"
    },
    "Turn a Log Into a Plank": {},
    "Visit Death's Domain": {},
    "Visit the Rune Essence Mine": {},
    "Achieve Your First Level 30": {},
    "Achieve Your First Level 40": {},
    "Achieve Your First Level 50": {},
    "Reach Total Level 750": {},
    "Reach Total Level 1000": {},
    "Reach Total Level 1250": {},
    "Reach Base Level 30": {},
    "Reach Base Level 40": {},
    "Reach Base Level 50": {},
    "Pickpocket a Guard": {
        "Skill1": "Thieving",
        "Level1": "40"
    },
    "Obtain 800 Coins From Coin Pouches At Once": {
        "Skill1": "Thieving",
        "Level1": "40"
    },
    "Pickpocket a Ranarr Seed": {
        "Skill1": "Thieving",
        "Level1": "38"
    },
    "Harvest an Irit Leaf": {
        "Skill1": "Farming",
        "Level1": "44"
    },
    "Fill a Bucket With Supercompost": {},
    "Check a grown Fruit Tree": {
        "Skill1": "Farming",
        "Level1": "27"
    },
    "Chop 100 Willow Logs": {
        "Skill1": "Woodcutting",
        "Level1": "30"
    },
    "Chop Some Logs With a Rune Axe": {
        "Skill1": "Woodcutting",
        "Level1": "41"
    },
    "Build a Waka Canoe": {
        "Skill1": "Woodcutting",
        "Level1": "57"
    },
    "Ferment 100 Jugs of Wine": {
        "Skill1": "Cooking",
        "Level1": "35"
    },
    "Cook 100 Lobsters": {
        "Skill1": "Cooking",
        "Level1": "40"
    },
    "Make a Pineapple Pizza": {
        "Skill1": "Cooking",
        "Level1": "65"
    },
    "Mine 50 Iron Ore": {
        "Skill1": "Mining",
        "Level1": "15"
    },
    "Mine some Ore With a Rune Pickaxe": {
        "Skill1": "Mining",
        "Level1": "41"
    },
    "Obtain a Clue Geode While Mining": {},
    "Fletch a Willow Shortbow": {
        "Skill1": "Fletching",
        "Level1": "35"
    },
    "Create a Mithril Grapple": {
        "Skill1": "Fletching",
        "Level1": "59"
    },
    "Fletch some Broad Arrows or Bolts": {
        "Skill1": "Fletching",
        "Level1": "52"
    },
    "Unlock Bigger and Badder": {},
    "Slay 250 Creatures": {},
    "Defeat a Superior Slayer Creature": {
        "Skill1": "Slayer",
        "Level1": "5"
    },
    "Craft 100 Unpowered Orbs": {
        "Skill1": "Crafting",
        "Level1": "46"
    },
    "Craft an Emerald Ring": {
        "Skill1": "Crafting",
        "Level1": "27"
    },
    "Craft a Ruby Amulet": {
        "Skill1": "Crafting",
        "Level1": "50"
    },
    "Catch 100 Lobsters": {
        "Skill1": "Fishing",
        "Level1": "40"
    },
    "Catch 50 Swordfish": {
        "Skill1": "Fishing",
        "Level1": "50"
    },
    "Catch 50 Salmon": {
        "Skill1": "Fishing",
        "Level1": "30"
    },
    "Smith a Steel Platebody": {
        "Skill1": "Smithing",
        "Level1": "48"
    },
    "Smelt a Steel Bar": {
        "Skill1": "Smithing",
        "Level1": "30"
    },
    "Build a Mahogany Portal": {
        "Skill1": "Construction",
        "Level1": "65"
    },
    "Build an Oak Larder": {
        "Skill1": "Construction",
        "Level1": "33"
    },
    "Fill a Medium S.T.A.S.H. Unit": {
        "Skill1": "Construction",
        "Level1": "42"
    },
    "Craft 200 Essence Into Runes": {},
    "Craft 4 Runes With 1 Essence": {
        "Skill1": "Runecraft",
        "Level1": "33"
    },
    "Craft Any Combination Rune": {
        "Skill1": "Runecraft",
        "Level1": "6"
    },
    "Burn 100 Willow Logs": {
        "Skill1": "Firemaking",
        "Level1": "30"
    },
    "Equip a Harpie Bug Lantern": {
        "Skill1": "Firemaking",
        "Level1": "33",
        "Skill2": "Slayer",
        "Level2": "33"
    },
    "Light a Bullseye Lantern": {
        "Skill1": "Firemaking",
        "Level1": "49"
    },
    "Equip full Graahk, Larupia or Kyatt": {
        "Skill1": "Hunter",
        "Level1": "31"
    },
    "Catch a Swamp Lizard or Salamander": {
        "Skill1": "Hunter",
        "Level1": "29"
    },
    "Catch a Butterfly": {
        "Skill1": "Hunter",
        "Level1": "15"
    },
    "Complete 50 Laps of a Rooftop Agility Course": {
        "Skill1": "Agility",
        "Level1": "10"
    },
    "Make 30 Prayer Potions": {
        "Skill1": "Herblore",
        "Level1": "38"
    },
    "Clean a Grimy Avantoe": {
        "Skill1": "Herblore",
        "Level1": "48"
    },
    "Make a Potion With an Amulet of Chemistry": {
        "Skill1": "Crafting",
        "Level1": "34",
        "Skill2": "Magic",
        "Level2": "27"
    },
    "Reach Combat Level 50": {},
    "Reach Combat Level 75": {},
    "Perform a Special Attack": {},
    "Equip an Adamant Weapon": {
        "Skill1": "Attack",
        "Level1": "30"
    },
    "Equip a Rune Weapon": {
        "Skill1": "Attack",
        "Level1": "40"
    },
    "Equip a Full Adamant Set": {
        "Skill1": "Defence",
        "Level1": "30"
    },
    "Equip a Full Rune Set": {
        "Skill1": "Defence",
        "Level1": "40"
    },
    "Equip a Full Green Dragonhide Set": {
        "Skill1": "Ranged",
        "Level1": "40",
        "Skill2": "Defence",
        "Level2": "40"
    },
    "Equip a Full Blue Dragonhide Set": {
        "Skill1": "Ranged",
        "Level1": "50",
        "Skill2": "Defence",
        "Level2": "40"
    },
    "Equip a Full Red Dragonhide Set": {
        "Skill1": "Ranged",
        "Level1": "60",
        "Skill2": "Defence",
        "Level2": "40"
    },
    "Equip a Yew Shortbow": {
        "Skill1": "Ranged",
        "Level1": "60"
    },
    "Equip an Elemental Battlestaff or Mystic Staff": {
        "Skill1": "Magic",
        "Level1": "30",
        "Skill2": "Attack",
        "Level2": "40"
    },
    "Cast a Blast Spell": {
        "Skill1": "Magic",
        "Level1": "41"
    },
    "Teleport Using Law Runes": {
        "Skill1": "Magic",
        "Level1": "25"
    },
    "Cast High Level Alchemy": {
        "Skill1": "Magic",
        "Level1": "55"
    },
    "Equip a Piece of a Mystic Set": {
        "Skill1": "Magic",
        "Level1": "40",
        "Skill2": "Defence",
        "Level2": "20"
    },
    "Use the Protect from Melee Prayer": {
        "Skill1": "Prayer",
        "Level1": "43"
    },
    "Bury Some Wyvern or Dragon Bones": {},
    "Reach a Prayer Bonus of 15": {},
    "Defeat a Lesser Demon": {},
    "Defeat an Adult Chromatic Dragon": {},
    "Complete a Medium Clue Scroll": {},
    "Complete a Hard Clue Scroll": {},
    "Gain a Unique Item From a Medium Clue": {},
    "Gain a Unique Item From a Hard Clue": {},
    "Gain 10 Unique Items From Beginner Clues": {},
    "Gain 10 Unique Items From Easy Clues": {},
    "Gain 10 Unique Items From Medium Clues": {},
    "Gain 5 Unique Items From Hard Clues": {},
    "Fill 5 Beginner Clue Collection Log Slots": {},
    "Fill 5 Easy Clue Collection Log Slots": {},
    "Fill 5 Medium Clue Collection Log Slots": {},
    "Fill 3 Hard Clue Collection Log Slots": {},
    "Fill 3 Elite Clue Collection Log Slots": {},
    "Equip a Trimmed Amulet": {},
    "Complete the Medium Western Provinces Diary": {
        "Notes": "See diary page"
    },
    "Achieve Your First Level 60": {},
    "Achieve Your First Level 70": {},
    "Achieve Your First Level 80": {},
    "Reach Total Level 1500": {},
    "Reach Total Level 1750": {},
    "Reach Base Level 60": {},
    "Reach Base Level 70": {},
    "Steal From a Gem Stall": {
        "Skill1": "Thieving",
        "Level1": "75"
    },
    "Check a grown Palm Tree": {
        "Skill1": "Farming",
        "Level1": "68"
    },
    "Dig Up Some Magic Roots": {
        "Skill1": "Farming",
        "Level1": "75"
    },
    "Chop 75 Magic Logs": {
        "Skill1": "Woodcutting",
        "Level1": "75"
    },
    "Cook 100 Sharks": {
        "Skill1": "Cooking",
        "Level1": "80"
    },
    "Mine 50 Adamantite Ore": {
        "Skill1": "Mining",
        "Level1": "70"
    },
    "Fletch a Magic Shortbow": {
        "Skill1": "Fletching",
        "Level1": "80"
    },
    "Fletch a Rune Crossbow": {
        "Skill1": "Fletching",
        "Level1": "91"
    },
    "Defeat a Slayer Boss": {
        "Skill1": "Slayer",
        "Level1": "75"
    },
    "Complete 50 Slayer Tasks": {},
    "Complete 100 Slayer Tasks": {},
    "Defeat 10 Superior Slayer Creatures": {
        "Skill1": "Slayer",
        "Level1": "5"
    },
    "Defeat 20 Superior Slayer Creatures": {
        "Skill1": "Slayer",
        "Level1": "5"
    },
    "Craft a Dragonstone Amulet": {
        "Skill1": "Crafting",
        "Level1": "80"
    },
    "Craft 30 Blue Dragonhide Bodies": {
        "Skill1": "Crafting",
        "Level1": "71"
    },
    "Catch 100 Shark": {
        "Skill1": "Fishing",
        "Level1": "76"
    },
    "Smelt a Runite Bar": {
        "Skill1": "Smithing",
        "Level1": "85"
    },
    "Fill a Hard S.T.A.S.H. Unit": {
        "Skill1": "Construction",
        "Level1": "55"
    },
    "Build an Achievement Gallery": {
        "Skill1": "Construction",
        "Level1": "80"
    },
    "Craft 2500 Essence Into Runes": {},
    "Burn 100 Yew Logs": {
        "Skill1": "Firemaking",
        "Level1": "60"
    },
    "Burn Some Magic Logs": {
        "Skill1": "Firemaking",
        "Level1": "75"
    },
    "Catch a Dragon Impling": {
        "Skill1": "Hunter",
        "Level1": "83"
    },
    "Complete 250 Laps of a Rooftop Agility Course": {
        "Skill1": "Agility",
        "Level1": "10"
    },
    "Make a Saradomin Brew": {
        "Skill1": "Herblore",
        "Level1": "81"
    },
    "Clean 100 Grimy Dwarf Weed": {
        "Skill1": "Herblore",
        "Level1": "70"
    },
    "Reach Combat Level 100": {},
    "Reach Combat Level 110": {},
    "Equip a Dragon Weapon": {
        "Skill1": "Attack",
        "Level1": "60"
    },
    "Equip a Full Black Dragonhide Set": {
        "Skill1": "Ranged",
        "Level1": "70",
        "Skill2": "Defence",
        "Level2": "40"
    },
    "Equip a Magic Shortbow": {
        "Skill1": "Ranged",
        "Level1": "50"
    },
    "Equip a Rune Crossbow": {
        "Skill1": "Ranged",
        "Level1": "61"
    },
    "Equip a Combination Battlestaff or Mystic Staff": {
        "Skill1": "Magic",
        "Level1": "30",
        "Skill2": "Attack",
        "Level2": "30"
    },
    "Cast a Wave Spell": {
        "Skill1": "Magic",
        "Level1": "62"
    },
    "Cast a Surge Spell": {
        "Skill1": "Magic",
        "Level1": "81"
    },
    "Restore 75 Prayer Points at an Altar": {
        "Skill1": "Prayer",
        "Level1": "75"
    },
    "Reach a Prayer Bonus of 30": {},
    "Complete an Elite Clue Scroll": {},
    "Complete a Master Clue Scroll": {},
    "Gain a Unique Item From an Elite Clue": {},
    "Gain a Unique Item From a Master Clue": {},
    "Gain 35 Unique Items From Beginner Clues": {},
    "Gain 35 Unique Items From Easy Clues": {},
    "Gain 25 Unique Items From Medium Clues": {},
    "Gain 20 Unique Items From Hard Clues": {},
    "Gain 10 Unique Items From Elite Clues": {},
    "Gain 10 Unique Items From Master Clues": {},
    "Fill 10 Beginner Clue Collection Log Slots": {},
    "Fill 20 Easy Clue Collection Log Slots": {},
    "Fill 20 Medium Clue Collection Log Slots": {},
    "Fill 15 Hard Clue Collection Log Slots": {},
    "Fill 10 Elite Clue Collection Log Slots": {},
    "Fill 5 Master Clue Collection Log Slots": {},
    "Equip a Full Gilded or Trimmed Wizard Set": {},
    "Equip a Full Gilded Set": {},
    "Equip a Full Vestment Set": {},
    "Equip a Full God Rune Set": {},
    "Equip a Full God Dragonhide Set": {},
    "Equip an Ornament Kit Item": {},
    "Equip Some Ranger Boots": {},
    "Complete the Hard Western Provinces Diary": {
        "Notes": "See diary page"
    },
    "Achieve Your First Level 90": {},
    "Achieve Your First Level 95": {},
    "Reach Total Level 2000": {},
    "Reach Total Level 2100": {},
    "Reach Total Level 2200": {},
    "Reach Base Level 80": {},
    "Reach Base Level 90": {},
    "Reach Level 99 Attack": {
        "Skill1": "Attack",
        "Level1": "99"
    },
    "Obtain 25 Million Attack XP": {
        "Skill1": "Attack",
        "Level1": "99"
    },
    "Reach Level 99 Strength": {
        "Skill1": "Strength",
        "Level1": "99"
    },
    "Obtain 25 Million Strength XP": {
        "Skill1": "Strength",
        "Level1": "99"
    },
    "Reach Level 99 Defence": {
        "Skill1": "Defence",
        "Level1": "99"
    },
    "Obtain 25 Million Defence XP": {
        "Skill1": "Defence",
        "Level1": "99"
    },
    "Reach Level 99 Ranged": {
        "Skill1": "Ranged",
        "Level1": "99"
    },
    "Obtain 25 Million Ranged XP": {
        "Skill1": "Ranged",
        "Level1": "99"
    },
    "Reach Level 99 Prayer": {
        "Skill1": "Prayer",
        "Level1": "99"
    },
    "Obtain 25 Million Prayer XP": {
        "Skill1": "Prayer",
        "Level1": "99"
    },
    "Reach Level 99 Magic": {
        "Skill1": "Magic",
        "Level1": "99"
    },
    "Obtain 25 Million Magic XP": {
        "Skill1": "Magic",
        "Level1": "99"
    },
    "Reach Level 99 Runecraft": {
        "Skill1": "Runecraft",
        "Level1": "99"
    },
    "Obtain 25 Million Runecraft XP": {
        "Skill1": "Runecraft",
        "Level1": "99"
    },
    "Reach Level 99 Construction": {
        "Skill1": "Construction",
        "Level1": "99"
    },
    "Obtain 25 Million Construction XP": {
        "Skill1": "Construction",
        "Level1": "99"
    },
    "Reach Level 99 Hitpoints": {
        "Skill1": "Hitpoints",
        "Level1": "99"
    },
    "Obtain 25 Million Hitpoints XP": {
        "Skill1": "Hitpoints",
        "Level1": "99"
    },
    "Reach Level 99 Agility": {
        "Skill1": "Agility",
        "Level1": "99"
    },
    "Obtain 25 Million Agility XP": {
        "Skill1": "Agility",
        "Level1": "99"
    },
    "Reach Level 99 Herblore": {
        "Skill1": "Herblore",
        "Level1": "99"
    },
    "Obtain 25 Million Herblore XP": {
        "Skill1": "Herblore",
        "Level1": "99"
    },
    "Reach Level 99 Thieving": {
        "Skill1": "Thieving",
        "Level1": "99"
    },
    "Obtain 25 Million Thieving XP": {
        "Skill1": "Thieving",
        "Level1": "99"
    },
    "Reach Level 99 Crafting": {
        "Skill1": "Crafting",
        "Level1": "99"
    },
    "Obtain 25 Million Crafting XP": {
        "Skill1": "Crafting",
        "Level1": "99"
    },
    "Reach Level 99 Fletching": {
        "Skill1": "Fletching",
        "Level1": "99"
    },
    "Obtain 25 Million Fletching XP": {
        "Skill1": "Fletching",
        "Level1": "99"
    },
    "Reach Level 99 Slayer": {
        "Skill1": "Slayer",
        "Level1": "99"
    },
    "Obtain 25 Million Slayer XP": {
        "Skill1": "Slayer",
        "Level1": "99"
    },
    "Reach Level 99 Hunter": {
        "Skill1": "Hunter",
        "Level1": "99"
    },
    "Obtain 25 Million Hunter XP": {
        "Skill1": "Hunter",
        "Level1": "99"
    },
    "Reach Level 99 Mining": {
        "Skill1": "Mining",
        "Level1": "99"
    },
    "Obtain 25 Million Mining XP": {
        "Skill1": "Mining",
        "Level1": "99"
    },
    "Reach Level 99 Smithing": {
        "Skill1": "Smithing",
        "Level1": "99"
    },
    "Obtain 25 Million Smithing XP": {
        "Skill1": "Smithing",
        "Level1": "99"
    },
    "Reach Level 99 Fishing": {
        "Skill1": "Fishing",
        "Level1": "99"
    },
    "Obtain 25 Million Fishing XP": {
        "Skill1": "Fishing",
        "Level1": "99"
    },
    "Reach Level 99 Cooking": {
        "Skill1": "Cooking",
        "Level1": "99"
    },
    "Obtain 25 Million Cooking XP": {
        "Skill1": "Cooking",
        "Level1": "99"
    },
    "Reach Level 99 Firemaking": {
        "Skill1": "Firemaking",
        "Level1": "99"
    },
    "Obtain 25 Million Firemaking XP": {
        "Skill1": "Firemaking",
        "Level1": "99"
    },
    "Reach Level 99 Woodcutting": {
        "Skill1": "Woodcutting",
        "Level1": "99"
    },
    "Obtain 25 Million Woodcutting XP": {
        "Skill1": "Woodcutting",
        "Level1": "99"
    },
    "Reach Level 99 Farming": {
        "Skill1": "Farming",
        "Level1": "99"
    },
    "Obtain 25 Million Farming XP": {
        "Skill1": "Farming",
        "Level1": "99"
    },
    "Obtain a Skilling Pet": {},
    "Travel Between Your Spirit Trees": {
        "Skill1": "Farming",
        "Level1": "91"
    },
    "Slay an Abyssal Demon": {
        "Skill1": "Slayer",
        "Level1": "85"
    },
    "Complete 200 Slayer Tasks": {},
    "Defeat 50 Superior Slayer Creatures": {
        "Skill1": "Slayer",
        "Level1": "5"
    },
    "Craft an Onyx Amulet": {
        "Skill1": "Crafting",
        "Level1": "90"
    },
    "Smith a Dragonfire Shield": {
        "Skill1": "Smithing",
        "Level1": "90"
    },
    "Catch a Lucky Impling Bare-Handed": {
        "Skill1": "Hunter",
        "Level1": "99"
    },
    "Make a Super Combat Potion": {
        "Skill1": "Herblore",
        "Level1": "90"
    },
    "Obtain a Boss Pet": {},
    "Equip a Full Dragon Set": {
        "Skill1": "Defence",
        "Level1": "60"
    },
    "Reach Combat Level 120": {},
    "Reach Combat Level 126": {},
    "Add a Jar to a Display Case": {},
    "Equip an Abyssal Whip": {
        "Skill1": "Attack",
        "Level1": "70"
    },
    "Gain 50 Unique Items From Hard Clues": {},
    "Gain 25 Unique Items From Elite Clues": {},
    "Gain 25 Unique Items From Master Clues": {},
    "Fill Every Beginner Clue Collection Log Slot": {},
    "Fill 50 Easy Clue Collection Log Slots": {},
    "Fill 40 Medium Clue Collection Log Slots": {},
    "Fill 30 Hard Clue Collection Log Slots": {},
    "Fill 25 Elite Clue Collection Log Slots": {},
    "Fill 25 Master Clue Collection Log Slots": {},
    "Use the Explore Emote": {},
    "Read a Clueless Scroll": {},
    "Equip a Heavy Casket": {},
    "Equip a Scroll Sack": {},
    "Transform into Uri": {},
    "Complete the Elite Western Provinces Diary": {
        "Notes": "See diary page"
    },
    "Reach Total Level 2277": {},
    "Reach Base Level 95": {},
    "Use the Range in Lumbridge Castle": {},
    "Pickpocket a H.A.M. Member": {
        "Skill1": "Thieving",
        "Level1": "15"
    },
    "Steal From the Varrock Tea Stall": {
        "Skill1": "Thieving",
        "Level1": "5"
    },
    "Complete the Draynor Agility Course": {
        "Skill1": "Agility",
        "Level1": "10"
    },
    "Craft 50 Water Runes": {
        "Skill1": "Runecraft",
        "Level1": "5"
    },
    "Complete the Easy Varrock Diary": {
        "Notes": "See diary page"
    },
    "Defeat the Lesser Demon in the Wizards' Tower": {},
    "Receive a Slayer Task From Vannaka": {},
    "Complete the Easy Lumbridge & Draynor Diary": {
        "Notes": "See diary page"
    },
    "Complete Rune Mysteries": {},
    "Enter Zanaris": {},
    "Travel to Fossil Island": {},
    "Pet a Stray Dog in Varrock": {},
    "Complete Sheep Shearer": {},
    "Complete Gertrude's Cat": {},
    "Complete Romeo & Juliet": {},
    "Drink From the Tears of Guthix": {},
    "Complete Vampyre Slayer": {},
    "Fully Unlock the Mycelium Transportation System": {},
    "Build a Bank on Fossil Island": {
        "Skill1": "Construction",
        "Level1": "21"
    },
    "Use a Fairy Ring": {},
    "Complete the Natural History Quiz": {},
    "Enter Draynor Manor": {},
    "Equip Some Fancy Boots or Fighting Boots": {},
    "Dismantle 20 Filled Bird Houses": {
        "Skill1": "Hunter",
        "Level1": "5",
        "Skill2": "Crafting",
        "Level2": "5"
    },
    "Build a Yew Bird House": {
        "Skill1": "Hunter",
        "Level1": "59",
        "Skill2": "Crafting",
        "Level2": "60"
    },
    "Catch 50 Implings in Puro-Puro": {
        "Skill1": "Hunter",
        "Level1": "17"
    },
    "Complete a Volcanic Mine Game": {
        "Skill1": "Mining",
        "Level1": "50"
    },
    "Enter the Cooks' Guild": {
        "Skill1": "Cooking",
        "Level1": "32"
    },
    "Pickpocket a Varrock Guard": {
        "Skill1": "Thieving",
        "Level1": "40"
    },
    "Pickpocket a Bullseye Lantern From a Cave Goblin": {
        "Skill1": "Thieving",
        "Level1": "36"
    },
    "Complete 30 Laps of the Draynor Agility Course": {
        "Skill1": "Agility",
        "Level1": "10"
    },
    "Craft 50 Cosmic Runes": {
        "Skill1": "Runecraft",
        "Level1": "59"
    },
    "Use Enriched Bones on the Strange Machine": {},
    "Chop a Sulliuscep Cap": {
        "Skill1": "Woodcutting",
        "Level1": "65"
    },
    "Complete the Medium Varrock Diary": {
        "Notes": "See diary page"
    },
    "Defeat a Fossil Island Wyvern": {
        "Skill1": "Slayer",
        "Level1": "66"
    },
    "Defeat Obor": {},
    "Defeat a Wall Beast": {
        "Skill1": "Slayer",
        "Level1": "35"
    },
    "Defeat Bryophyta": {},
    "Equip a Dorgeshuun Crossbow": {
        "Skill1": "Ranged",
        "Level1": "28"
    },
    "Complete the Medium Lumbridge & Draynor Diary": {
        "Notes": "See diary page"
    },
    "Equip Some Mithril Gloves": {},
    "Complete The Lost Tribe": {},
    "Complete Death to the Dorgeshuun": {},
    "Complete Demon Slayer": {},
    "Use a Digsite Pendant to Teleport to Fossil Island": {
        "Skill1": "Crafting",
        "Level1": "40",
        "Skill2": "Magic",
        "Level2": "49"
    },
    "Complete a Soul's Bane": {},
    "Build a Magic Bird House": {
        "Skill1": "Hunter",
        "Level1": "74",
        "Skill2": "Crafting",
        "Level2": "75"
    },
    "Complete the Hard Varrock Diary": {
        "Notes": "See diary page"
    },
    "Catch 200 Implings in Puro-Puro": {
        "Skill1": "Hunter",
        "Level1": "17"
    },
    "Buy an Ash Covered Tome": {
        "Skill1": "Mining",
        "Level1": "50"
    },
    "Check a grown Magic Tree in Lumbridge": {
        "Skill1": "Farming",
        "Level1": "75"
    },
    "Check a grown Mahogany Tree": {
        "Skill1": "Farming",
        "Level1": "55"
    },
    "Steal a Diamond in Dorgesh-Kaan": {
        "Skill1": "Thieving",
        "Level1": "78"
    },
    "Take the Advanced Shortcut to the Cosmic Altar": {
        "Skill1": "Agility",
        "Level1": "66"
    },
    "Defeat a Rune Dragon": {},
    "Equip a Hill Giant Club": {
        "Skill1": "Attack",
        "Level1": "40"
    },
    "Equip Bryophyta's Staff": {
        "Skill1": "Attack",
        "Level1": "30",
        "Skill2": "Magic",
        "Level2": "30"
    },
    "Defeat the Abyssal Sire": {
        "Skill1": "Slayer",
        "Level1": "85"
    },
    "Defeat an Ancient Wyvern": {
        "Skill1": "Slayer",
        "Level1": "82"
    },
    "Complete the Hard Lumbridge & Draynor Diary": {
        "Notes": "See diary page"
    },
    "Catch a Herbiboar 100 Times": {
        "Skill1": "Hunter",
        "Level1": "80"
    },
    "Catch a Herbiboar 250 Times": {
        "Skill1": "Hunter",
        "Level1": "80"
    },
    "Catch a Herbiboar 500 Times": {
        "Skill1": "Hunter",
        "Level1": "80"
    },
    "Receive a Torstol From a Herbiboar": {
        "Skill1": "Hunter",
        "Level1": "80",
        "Skill2": "Herblore",
        "Level2": "77"
    },
    "Complete the Elite Varrock Diary": {
        "Notes": "See diary page"
    },
    "Mine a Runite Ore Fragment": {
        "Skill1": "Mining",
        "Level1": "85"
    },
    "Equip a Dragon Crossbow": {
        "Skill1": "Fletching",
        "Level1": "78"
    },
    "Equip a Dragonfire Shield": {
        "Skill1": "Smithing",
        "Level1": "90",
        "Skill2": "Defence",
        "Level2": "75"
    },
    "Equip an Ancient Wyvern Shield": {
        "Skill1": "Smithing",
        "Level1": "66",
        "Skill2": "Defence",
        "Level2": "75",
        "Skill3": "Magic",
        "Level3": "70"
    },
    "Equip an Abyssal Bludgeon": {
        "Skill1": "Slayer",
        "Level1": "85"
    },
    "Equip an Abyssal Dagger": {
        "Skill1": "Slayer",
        "Level1": "85"
    },
    "Offer an Unsired to the Font of Consumption": {
        "Skill1": "Slayer",
        "Level1": "85"
    },
    "Defeat the Abyssal Sire 100 Times": {
        "Skill1": "Slayer",
        "Level1": "85"
    },
    "Defeat the Abyssal Sire 250 Times": {
        "Skill1": "Slayer",
        "Level1": "85"
    },
    "Defeat the Abyssal Sire 500 Times": {
        "Skill1": "Slayer",
        "Level1": "85"
    },
    "Complete the Elite Lumbridge & Draynor Diary": {
        "Notes": "See diary page"
    },
    "Equip a Dragon Platebody or Dragon Kiteshield": {
        "Skill1": "Smithing",
        "Level1": "90",
        "Skill2": "Defence",
        "Level2": "75"
    },
    "Receive an Agility Arena Ticket": {},
    "Catch a Karambwanji": {
        "Skill1": "Fishing",
        "Level1": "5"
    },
    "Defeat a TzHaar": {},
    "Receive a Slayer Task From Duradel": {
        "Skill1": "Combat",
        "Level1": "100",
        "Skill2": "Slayer",
        "Level2": "50"
    },
    "Defeat a Greater Demon on Karamja": {},
    "Complete the Easy Karamja Diary": {
        "Notes": "See diary page"
    },
    "Fill a Crate With Bananas": {},
    "Pick a Pineapple on Karamja": {},
    "Enter the Brimhaven Dungeon": {},
    "Buy a Snapdragon From Pirate Jackie the Fruit": {},
    "Catch a Salmon on Karamja": {
        "Skill1": "Fishing",
        "Level1": "30"
    },
    "Craft 50 Nature Runes": {
        "Skill1": "Runecraft",
        "Level1": "44"
    },
    "Defeat a Steel Dragon on Karamja": {},
    "Complete the Medium Karamja Diary": {
        "Notes": "See diary page"
    },
    "Enter the Tai Bwo Wannai Hardwood Grove": {},
    "Equip a Matching Tribal Mask and Broodoo Shield": {},
    "Equip a Full Tai Bwo Wannai Villager Set": {},
    "Cook 100 Karambwans": {
        "Skill1": "Cooking",
        "Level1": "30"
    },
    "Take a Shortcut Across the Shilo Village River": {
        "Skill1": "Agility",
        "Level1": "77"
    },
    "Catch 100 Karambwans": {
        "Skill1": "Fishing",
        "Level1": "65"
    },
    "Check a grown Calquat Tree": {
        "Skill1": "Farming",
        "Level1": "72"
    },
    "Equip a Full Obsidian Armour Set": {
        "Skill1": "Defence",
        "Level1": "70"
    },
    "Survive a Hit From TzTok-Jad Without Prayer": {},
    "Equip Some Dragon Platelegs or a Dragon Plateskirt": {
        "Skill1": "Defence",
        "Level1": "60"
    },
    "Equip an Obsidian Cape": {},
    "Equip a Toktz-Ket-Xil": {
        "Skill1": "Defence",
        "Level1": "60"
    },
    "Equip a Tzhaar-Ket-Om": {
        "Skill1": "Strength",
        "Level1": "60"
    },
    "Equip a Toktz-Xil-Ak": {
        "Skill1": "Attack",
        "Level1": "60"
    },
    "Equip a Toktz-Xil-Ek": {
        "Skill1": "Attack",
        "Level1": "60"
    },
    "Complete the Hard Karamja Diary": {
        "Notes": "See diary page"
    },
    "Equip a Red Topaz Machete": {},
    "Find a Gout Tubor": {},
    "Receive 60 Agility Arena Tickets With No Mistakes": {
        "Skill1": "Agility",
        "Level1": "40"
    },
    "Pickpocket a Diamond From a TzHaar": {
        "Skill1": "Thieving",
        "Level1": "90"
    },
    "Equip a Fire Cape": {},
    "Complete the Fight Caves in 35:00": {},
    "Sacrifice a Fire Cape to Access the Inferno": {},
    "Complete the Fight Caves 5 Times": {},
    "Complete the Fight Caves 15 Times": {},
    "Complete the Fight Caves 30 Times": {},
    "Complete the Inferno 5 Times": {},
    "Complete the Inferno 10 Times": {},
    "Complete the Inferno 20 Times": {},
    "Complete the Elite Karamja Diary": {
        "Notes": "See diary page"
    },
    "Purchase an Onyx in Mor Ul Rek": {},
    "Trade 1,000 Agility Arena Tickets for XP": {},
    "Equip an Infernal Cape": {},
    "Complete the Fight Caves in 25:00": {},
    "Complete the Inferno in 75:00": {},
    "Craft an Air Rune": {
        "Skill1": "Runecraft",
        "Level1": "1"
    },
    "Move Your House to Taverley": {
        "Skill1": "Construction",
        "Level1": "10"
    },
    "Receive a Slayer Task From Turael or Spria": {
        "Skill1": "Slayer",
        "Level1": "1"
    },
    "Defeat a Troll in Asgarnia": {},
    "Defeat a Blue Dragon in Asgarnia": {},
    "Defeat a Black Demon in Asgarnia": {},
    "Complete the Easy Falador Diary": {
        "Notes": "See diary page"
    },
    "Unlock a Gate in Taverley Dungeon": {},
    "Enter the Taverly Dungeon": {},
    "Complete a Game of Novice Pest Control": {
        "Skill1": "Combat",
        "Level1": "40"
    },
    "Complete the Falador Agility Course": {
        "Skill1": "Agility",
        "Level1": "50"
    },
    "Obtain 20 Golden Nuggets": {
        "Skill1": "Mining",
        "Level1": "30"
    },
    "Enter the Crafting Guild": {
        "Skill1": "Crafting",
        "Level1": "40"
    },
    "Craft a Body Rune": {
        "Skill1": "Runecraft",
        "Level1": "20"
    },
    "Harvest Any Herb at the Troll Stronghold": {
        "Skill1": "Farming",
        "Level1": "1"
    },
    "Defeat the Giant Mole": {},
    "Defeat a Skeletal Wyvern": {
        "Skill1": "Slayer",
        "Level1": "72"
    },
    "Equip Some Granite Legs": {
        "Skill1": "Slayer",
        "Level1": "72"
    },
    "Charge an Amulet of Glory in the Heroes' Guild": {
        "Notes": "See quest page"
    },
    "Defeat 30 Black Dragons in Asgarnia": {},
    "Complete the Medium Falador Diary": {
        "Notes": "See diary page"
    },
    "Enter the Warriors' Guild": {
        "Notes": "Combination of Attack and Strength >= 130"
    },
    "Complete A Porcine of Interest": {
        "Notes": "See quest page"
    },
    "Defeat Some Animated Rune Armour": {},
    "Open the Crystal Chest": {},
    "Complete a Game of Intermediate Pest Control": {
        "Skill1": "Combat",
        "Level1": "70"
    },
    "Equip a Full Graceful Outfit": {},
    "Equip a Full Rogue Outfit": {
        "Skill1": "Thieving",
        "Level1": "50",
        "Skill2": "Agility",
        "Level2": "50"
    },
    "Equip a Full Prospector Outfit": {
        "Skill1": "Mining",
        "Level1": "30"
    },
    "Craft 50 Law Runes": {
        "Skill1": "Runecraft",
        "Level1": "54"
    },
    "Make 20 Ranging Potions": {
        "Skill1": "Herblore",
        "Level1": "72"
    },
    "Make 20 Stamina Potions": {
        "Skill1": "Herblore",
        "Level1": "77"
    },
    "Equip a Dragon Defender": {},
    "Defeat K'ril Tsutsaroth": {
        "Skill1": "Hitpoints",
        "Level1": "70"
    },
    "Defeat General Graardor": {
        "Skill1": "Strength",
        "Level1": "70"
    },
    "Defeat Kree'arra": {
        "Skill1": "Ranged",
        "Level1": "70"
    },
    "Defeat Commander Zilyana": {
        "Skill1": "Agility",
        "Level1": "70"
    },
    "Equip a Pair of Dragon Boots": {
        "Skill1": "Slayer",
        "Level1": "83"
    },
    "Complete the Hard Falador Diary": {
        "Notes": "See diary page"
    },
    "Equip a Full Void Knight Set": {},
    "Turn in 100 Mole Claws to Wyson the Gardener": {},
    "Keep the Veteran Void Knight Above 150 Hitpoints": {
        "Skill1": "Combat",
        "Level1": "100"
    },
    "Complete a Game of Veteran Pest Control": {
        "Skill1": "Combat",
        "Level1": "100"
    },
    "Equip an Infernal Tool": {},
    "Equip a Staff of the Dead": {
        "Skill1": "Attack",
        "Level1": "75",
        "Skill2": "Magic",
        "Level2": "75"
    },
    "Equip a Zamorakian Spear": {
        "Skill1": "Attack",
        "Level1": "70"
    },
    "Equip a Piece of the Armadyl Armour Set": {
        "Skill1": "Ranged",
        "Level1": "70",
        "Skill2": "Defence",
        "Level2": "70"
    },
    "Equip a Saradomin Sword": {
        "Skill1": "Attack",
        "Level1": "70"
    },
    "Equip a Piece of the Bandos Armour Set": {
        "Skill1": "Defence",
        "Level1": "65"
    },
    "Equip an Armadyl Crossbow": {
        "Skill1": "Ranged",
        "Level1": "70"
    },
    "Equip Some Primordial, Pegasian or Eternal Boots": {
        "Skill1": "Defence",
        "Level1": "75"
    },
    "Equip a Godsword": {
        "Skill1": "Attack",
        "Level1": "75"
    },
    "Defeat Cerberus": {
        "Skill1": "Slayer",
        "Level1": "91"
    },
    "Defeat Any God Wars Dungeon Boss 100 Times": {},
    "Defeat Any God Wars Dungeon Boss 250 Times": {},
    "Defeat Any God Wars Dungeon Boss 500 Times": {},
    "Defeat the Giant Mole 250 Times": {},
    "Defeat the Giant Mole 500 Times": {},
    "Defeat the Giant Mole 750 Times": {},
    "Complete the Elite Falador Diary": {
        "Notes": "See diary page"
    },
    "Defeat Cerberus Before She Summons Souls": {
        "Skill1": "Slayer",
        "Level1": "91"
    },
    "Equip Every Godsword": {
        "Skill1": "Attack",
        "Level1": "75"
    },
    "Equip a Full Armadyl Armour Set": {
        "Skill1": "Ranged",
        "Level1": "70",
        "Skill2": "Defence",
        "Level2": "70"
    },
    "Equip a Full Bandos Armour Set": {
        "Skill1": "Defence",
        "Level1": "65"
    },
    "Equip Some Primordial, Pegasian and Eternal Boots": {
        "Skill1": "Defence",
        "Level1": "75",
        "Skill2": "Strength",
        "Level2": "75",
        "Skill3": "Magic",
        "Level3": "75",
        "Skill4": "Ranged",
        "Level4": "75"
    },
    "Fremennik Provinces": {},
    "Switch to the Lunar Spellbook": {},
    "Defeat a Rock Crab in the Fremennik Province": {},
    "Defeat a Cockatrice in the Fremennik Province": {
        "Skill1": "Slayer",
        "Level1": "25"
    },
    "Defeat a Pyrefiend in the Fremennik Province": {
        "Skill1": "Slayer",
        "Level1": "30"
    },
    "Defeat a Troll in the Fremennik Province": {},
    "Complete the Easy Fremennik Diary": {
        "Notes": "See diary page"
    },
    "Deposit an Item Using Peer the Seer": {},
    "Use the Bank on Jatizso": {},
    "Use the Bank on Neitiznot": {},
    "Use the Bank on Lunar Isle": {},
    "Cast Moonclan Teleport": {
        "Skill1": "Magic",
        "Level1": "69"
    },
    "Move Your House to Rellekka": {
        "Skill1": "Construction",
        "Level1": "30"
    },
    "Craft 50 Astral Runes": {
        "Skill1": "Runecraft",
        "Level1": "40"
    },
    "Complete the Penguin Agility Course": {
        "Skill1": "Agility",
        "Level1": "30"
    },
    "Catch a Snowy Knight": {
        "Skill1": "Hunter",
        "Level1": "35"
    },
    "Unlock Free Use of the Blast Furnace": {
        "Skill1": "Smithing",
        "Level1": "60"
    },
    "Use Some Icy Basalt to Teleport to Weiss": {},
    "Defeat a Basilisk Knight": {
        "Skill1": "Slayer",
        "Level1": "60"
    },
    "Defeat a Kurask in the Fremennik Province": {
        "Skill1": "Slayer",
        "Level1": "70"
    },
    "Equip a Granite Shield": {
        "Skill1": "Defence",
        "Level1": "50",
        "Skill2": "Strength",
        "Level2": "50"
    },
    "Equip a Brine Sabre": {
        "Skill1": "Attack",
        "Level1": "40"
    },
    "Defeat a Dagannoth in the Fremennik Province": {},
    "Equip a Helm of Neitiznot": {},
    "Defeat a Turoth in the Fremennik Province": {
        "Skill1": "Slayer",
        "Level1": "55"
    },
    "Defeat a Jelly in the Fremennik Province": {
        "Skill1": "Slayer",
        "Level1": "52"
    },
    "Equip a Leaf-Bladed Sword": {
        "Skill1": "Attack",
        "Level1": "50",
        "Skill2": "Slayer",
        "Level2": "55"
    },
    "Complete the Medium Fremennik Diary": {
        "Notes": "See diary page"
    },
    "Complete Throne of Miscellania": {
        "Notes": "See quest page"
    },
    "Complete Royal Trouble": {
        "Notes": "See quest page"
    },
    "Complete Olaf's Quest": {
        "Notes": "See quest page"
    },
    "Cast Fertile Soil": {
        "Skill1": "Magic",
        "Level1": "83"
    },
    "Build a Gilded Altar": {
        "Skill1": "Construction",
        "Level1": "75"
    },
    "Complete the Rellekka Agility Course": {
        "Skill1": "Agility",
        "Level1": "80"
    },
    "Harvest a Snapdragon in Weiss": {
        "Skill1": "Farming",
        "Level1": "62"
    },
    "Trap a Sabre-Toothed Kyatt": {
        "Skill1": "Hunter",
        "Level1": "55"
    },
    "Use Your Portal Nexus to Teleport to Weiss": {
        "Skill1": "Construction",
        "Level1": "72"
    },
    "Defeat Vorkath": {},
    "Equip an Ava's Assembler": {},
    "Defeat Vorkath in 1:45": {},
    "Defeat the Dagannoth Kings Without Leaving": {},
    "Equip a Berserker Ring": {},
    "Equip a Warrior Ring": {},
    "Equip a Seers Ring": {},
    "Equip an Archers Ring": {},
    "Use the Special Attack of a Dragon Axe": {
        "Skill1": "Attack",
        "Level1": "60"
    },
    "Equip a Mud Battlestaff": {
        "Skill1": "Magic",
        "Level1": "30",
        "Skill2": "Attack",
        "Level2": "30"
    },
    "Equip a Seercull": {
        "Skill1": "Ranged",
        "Level1": "50"
    },
    "Equip a Leaf-Bladed Battleaxe": {
        "Skill1": "Attack",
        "Level1": "65",
        "Skill2": "Slayer",
        "Level2": "55"
    },
    "Equip a Full Skeletal Armour Set": {
        "Skill1": "Magic",
        "Level1": "40",
        "Skill2": "Defence",
        "Level2": "40"
    },
    "Equip a Full Spined Armour Set": {
        "Skill1": "Ranged",
        "Level1": "40",
        "Skill2": "Defence",
        "Level2": "40"
    },
    "Equip a Full Rockshell Armour Set": {
        "Skill1": "Defence",
        "Level1": "40"
    },
    "Complete the Hard Fremennik Diary": {
        "Notes": "See diary page"
    },
    "Collect Miscellania Resources at Full Approval": {},
    "Cast Spellbook Swap": {
        "Skill1": "Magic",
        "Level1": "96"
    },
    "Build a Gilded Portal Nexus": {
        "Skill1": "Construction",
        "Level1": "82"
    },
    "Equip a Dragonfire Ward": {
        "Skill1": "Ranged",
        "Level1": "75",
        "Skill2": "Defence",
        "Level2": "70"
    },
    "Create a Catherby Teleport Tablet": {
        "Skill1": "Magic"
    },
    "Equip a Dragonbone Necklace": {
        "Skill1": "Prayer",
        "Level1": "80"
    },
    "Defeat Vorkath in 1:00": {},
    "Equip Every Dagannoth King Ring": {},
    "Equip a Neitiznot Faceguard": {
        "Skill1": "Defence",
        "Level1": "70"
    },
    "Defeat Vorkath 5 Times Without Special Damage": {},
    "Defeat Vorkath 15 Times Without Leaving": {},
    "Defeat Vorkath 250 Times": {},
    "Defeat Vorkath 500 Times": {},
    "Defeat Vorkath 750 Times": {},
    "Defeat Each Dagannoth King 300 Times": {},
    "Defeat Each Dagannoth King 650 Times": {},
    "Defeat Each Dagannoth King 1000 Times": {},
    "Complete the Elite Fremennik Diary": {
        "Notes": "See diary page"
    },
    "Equip a Completed God Book": {},
    "Build a Demonic Throne": {
        "Skill1": "Construction",
        "Level1": "99"
    },
    "Equip Every Draconic Shield": {},
    "Defeat Vorkath in 0:45": {},
    "Equip Every Completed God Book": {},
    "Complete the Gnome Stronghold Agility Course": {
        "Skill1": "Agility",
        "Level1": "1"
    },
    "Catch a Crimson Swift in the Feldip Hills": {
        "Skill1": "Hunter",
        "Level1": "1"
    },
    "Complete a Fishing Trawler Game": {},
    "Receive a Slayer Task From Steve": {
        "Skill1": "Combat",
        "Level1": "85"
    },
    "Defeat a Tortoise With Riders in Kandarin": {},
    "Visit the Tree Gnome Village": {},
    "Visit the Tree Gnome Stronghold": {},
    "Complete Monk's Friend": {
        "Notes": "See quest page"
    },
    "Complete Tower of Life": {
        "Notes": "See quest page"
    },
    "Complete Sea Slug": {
        "Notes": "See quest page"
    },
    "Brimstail Rune Essence Mine teleport": {},
    "Equip a Marksman Chompy Hat": {},
    "Equip a Monkey Backpack": {},
    "Complete the Easy Ardougne Diary": {
        "Notes": "See diary page"
    },
    "Complete the Easy Kandarin Diary": {
        "Notes": "See diary page"
    },
    "Fletch 50 Maple Longbow (u) in Kandarin": {
        "Skill1": "Fletching",
        "Level1": "55"
    },
    "Pickpocket a Knight of Ardougne 50 Times": {
        "Skill1": "Thieving",
        "Level1": "55"
    },
    "Complete the Barbarian Outpost Agility Course": {
        "Skill1": "Agility",
        "Level1": "35"
    },
    "Trap a Spined Larupia in the Feldip Hills": {
        "Skill1": "Hunter",
        "Level1": "31"
    },
    "Equip a Spottier Cape": {
        "Skill1": "Hunter",
        "Level1": "66"
    },
    "Catch a Red Salamander": {
        "Skill1": "Hunter",
        "Level1": "59"
    },
    "Enter the Fishing Guild": {
        "Skill1": "Fishing",
        "Level1": "68"
    },
    "Move Your House to Yanille": {
        "Skill1": "Construction",
        "Level1": "50"
    },
    "Check a grown Papaya Tree in the Gnome Stronghold": {
        "Skill1": "Farming",
        "Level1": "57"
    },
    "Defeat a Mithril Dragon": {},
    "Equip a Dragon Scimitar": {
        "Skill1": "Attack",
        "Level1": "60"
    },
    "Set Up a Dwarf Cannon": {},
    "Enter the Ranging Guild": {
        "Skill1": "Ranged",
        "Level1": "40"
    },
    "Enter the Wizards' Guild": {
        "Skill1": "Magic",
        "Level1": "66"
    },
    "Defeat a Bloodveld in Kandarin": {
        "Skill1": "Slayer",
        "Level1": "50"
    },
    "Defeat an Aberrant Spectre in Kandarin": {
        "Skill1": "Slayer",
        "Level1": "60"
    },
    "Use the Chivalry Prayer": {
        "Skill1": "Prayer",
        "Level1": "60",
        "Skill2": "Defence",
        "Level2": "65"
    },
    "Equip an Iban's Staff (u)": {
        "Skill1": "Magic",
        "Level1": "50",
        "Skill2": "Attack",
        "Level2": "50"
    },
    "Win a Game of Castle Wars": {},
    "Complete Elemental Workshop II": {
        "Notes": "See quest page"
    },
    "Complete the Observatory Quest": {
        "Notes": "See quest page"
    },
    "Defeat the Penance Queen": {},
    "Complete the Medium Ardougne Diary": {
        "Notes": "See diary page"
    },
    "Equip an Ogre Forester Chompy Hat": {
        "Skill1": "Ranged",
        "Level1": "30",
        "Skill2": "Fletching",
        "Level2": "5"
    },
    "Equip a Karamja Monkey Backpack": {
        "Skill1": "Agility",
        "Level1": "48"
    },
    "Complete the Medium Kandarin Diary": {
        "Notes": "See diary page"
    },
    "Pickpocket a Hero": {
        "Skill1": "Thieving",
        "Level1": "80"
    },
    "Complete the Seers' Village Agility Course": {
        "Skill1": "Agility",
        "Level1": "60"
    },
    "Catch 50 Red Chinchompas in the Hunting Ground": {
        "Skill1": "Hunter",
        "Level1": "63"
    },
    "Catch a Monkfish": {
        "Skill1": "Fishing",
        "Level1": "62"
    },
    "Equip a Full Angler's Outfit": {},
    "Defeat a Demonic Gorilla": {},
    "Equip a Fighter Torso": {},
    "Defeat a Cave Kraken": {
        "Skill1": "Slayer",
        "Level1": "87",
        "Skill2": "Magic",
        "Level2": "50"
    },
    "Equip a Trident of the Seas": {
        "Skill1": "Magic",
        "Level1": "75"
    },
    "Use the Piety Prayer": {
        "Skill1": "Prayer",
        "Level1": "70",
        "Skill2": "Defence",
        "Level2": "70"
    },
    "Enter the Myths' Guild": {},
    "Complete the Hard Ardougne Diary": {
        "Notes": "See diary page"
    },
    "Reach Level 5 in Any Barbarian Assault Role": {},
    "Equip an Ogre Expert Chompy Hat": {
        "Skill1": "Ranged",
        "Level1": "30",
        "Skill2": "Fletching",
        "Level2": "5"
    },
    "Equip a Maniacal Monkey Backpack": {
        "Skill1": "Agility",
        "Level1": "48"
    },
    "Complete the Hard Kandarin Diary": {
        "Notes": "See diary page"
    },
    "Complete the Ardougne Agility Course": {
        "Skill1": "Agility",
        "Level1": "90"
    },
    "Check a grown Dragonfruit Tree in Catherby": {
        "Skill1": "Farming",
        "Level1": "81"
    },
    "Defeat a Smoke Devil": {
        "Skill1": "Slayer",
        "Level1": "93"
    },
    "Equip Some Zenyte Jewelry": {},
    "Equip a Heavy Ballista": {
        "Skill1": "Ranged",
        "Level1": "75"
    },
    "Equip an Abyssal Tentacle": {
        "Skill1": "Attack",
        "Level1": "75"
    },
    "Defeat the Thermonuclear Smoke Devil": {
        "Skill1": "Slayer",
        "Level1": "93"
    },
    "Equip an Occult Necklace": {
        "Skill1": "Magic",
        "Level1": "70"
    },
    "Equip a Dragon Full Helm": {},
    "Defeat the Kraken Boss 250 Times": {},
    "Defeat the Kraken Boss 500 Times": {},
    "Defeat the Kraken Boss 750 Times": {},
    "Defeat 300 Demonic Gorillas": {},
    "Defeat 750 Demonic Gorillas": {},
    "Defeat 1500 Demonic Gorillas": {},
    "Reach Level 5 in Every Barbarian Assault Role": {},
    "Equip a Dragon Archer Chompy Hat": {
        "Skill1": "Ranged",
        "Level1": "30",
        "Skill2": "Fletching",
        "Level2": "5"
    },
    "Equip a Kruk Jr. Monkey Backpack": {
        "Skill1": "Agility",
        "Level1": "48"
    },
    "Complete the Elite Kandarin Diary": {
        "Notes": "See diary page"
    },
    "Complete the Elite Ardougne Diary": {
        "Notes": "See diary page"
    },
    "Equip All Zenyte Jewelry": {},
    "Enhance a Trident of the Seas": {},
    "Equip an Expert Dragon Archer Chompy Hat": {},
    "Equip a Prince Awowogei Monkey Back": {
        "Skill1": "Agility",
        "Level1": "48"
    },
    "Complete Room 1 of Pyramid Plunder": {
        "Skill1": "Thieving",
        "Level1": "21"
    },
    "Complete Room 2 of Pyramid Plunder": {
        "Skill1": "Thieving",
        "Level1": "31"
    },
    "Pick a Winter Sq'irk": {},
    "Turn in a Winter Sq'irkjuice to Osman": {},
    "Complete the Al Kharid Agility Course": {
        "Skill1": "Agility",
        "Level1": "20"
    },
    "Craft a Fire Rune": {
        "Skill1": "Runecraft",
        "Level1": "14"
    },
    "Defeat an Al Kharid Warrior": {},
    "Complete the Easy Desert Diary": {
        "Notes": "See diary page"
    },
    "Go Through the Al Kharid Gate": {},
    "Tan a Cow Hide in the Kharidian Desert": {},
    "Use the Bank in Nardah": {},
    "Cut a Cactus in the Kharidian Desert": {},
    "Take a Carpet Ride from Pollnivneach to Sophanem": {},
    "Enter the Kalphite Lair": {},
    "Complete The Golem": {},
    "Complete Room 3 of Pyramid Plunder": {
        "Skill1": "Thieving",
        "Level1": "41"
    },
    "Complete Room 4 of Pyramid Plunder": {
        "Skill1": "Thieving",
        "Level1": "51"
    },
    "Complete Room 5 of Pyramid Plunder": {
        "Skill1": "Thieving",
        "Level1": "61"
    },
    "Pick a Spring Sq'irk": {
        "Skill1": "Thieving",
        "Level1": "25"
    },
    "Pick a Autumn Sq'irk": {
        "Skill1": "Thieving",
        "Level1": "45"
    },
    "Turn in 10 Spring Sq'irkjuices to Osman": {
        "Skill1": "Thieving",
        "Level1": "25"
    },
    "Pickpocket a Bandit in the Desert": {
        "Skill1": "Thieving",
        "Level1": "45"
    },
    "Smith 1000 Mithril Dart Tips": {
        "Skill1": "Smithing",
        "Level1": "54"
    },
    "Make a Combat Potion": {
        "Skill1": "Herblore",
        "Level1": "36"
    },
    "Defeat a Crocodile": {},
    "Turn in a Pyramid Top to Simon Templeton": {
        "Skill1": "Agility",
        "Level1": "30"
    },
    "Craft a Lava Rune at the Fire Altar": {
        "Skill1": "Runecraft",
        "Level1": "23"
    },
    "Catch 30 Orange Salamanders": {
        "Skill1": "Hunter",
        "Level1": "47"
    },
    "Mine 30 Chunks of Granite": {
        "Skill1": "Mining",
        "Level1": "45"
    },
    "Defeat a Scarab Mage": {},
    "Defeat a Kalphite Guardian": {},
    "Move Your House to Pollnivneach": {
        "Skill1": "Construction",
        "Level1": "20"
    },
    "Cast Ice Rush": {
        "Skill1": "Magic",
        "Level1": "58"
    },
    "Complete the Medium Desert Diary": {
        "Notes": "See diary page"
    },
    "Cast Bones to Peaches": {
        "Skill1": "Magic",
        "Level1": "60"
    },
    "Complete Spirits of the Elid": {},
    "Pray at the Elidinis Statuette": {},
    "Enter Sophanem": {},
    "Complete Shadow of the Storm": {},
    "Complete Room 6 of Pyramid Plunder": {
        "Skill1": "Thieving",
        "Level1": "71"
    },
    "Complete Room 7 of Pyramid Plunder": {
        "Skill1": "Thieving",
        "Level1": "81"
    },
    "Pick a Summer Sq'irk": {
        "Skill1": "Thieving",
        "Level1": "65"
    },
    "Turn in 25 Autumn Sq'irkjuices to Osman": {
        "Skill1": "Thieving",
        "Level1": "45"
    },
    "Pickpocket a Menaphite Thug 50 Times": {
        "Skill1": "Thieving",
        "Level1": "65"
    },
    "Make 20 Magic Potions": {
        "Skill1": "Herblore",
        "Level1": "76"
    },
    "Smith 1000 Adamant Dart Tips": {
        "Skill1": "Smithing",
        "Level1": "74"
    },
    "Check a grown Cactus": {
        "Skill1": "Farming",
        "Level1": "55"
    },
    "Check a grown Potato Cactus": {
        "Skill1": "Farming",
        "Level1": "64"
    },
    "Defeat a Dust Devil in the Kharidian Desert": {
        "Skill1": "Slayer",
        "Level1": "65"
    },
    "Cast Ice Burst": {
        "Skill1": "Magic",
        "Level1": "70"
    },
    "Cast Ice Blitz": {
        "Skill1": "Magic",
        "Level1": "82"
    },
    "Cast Smoke Barrage": {
        "Skill1": "Magic",
        "Level1": "86"
    },
    "Cast Shadow Barrage": {
        "Skill1": "Magic",
        "Level1": "88"
    },
    "Equip a Dragon 2H Sword": {},
    "Complete the Hard Desert Diary": {
        "Notes": "See diary page"
    },
    "Equip a Piece of the Infinity Robe Set": {
        "Skill1": "Magic",
        "Level1": "50",
        "Skill2": "Defence",
        "Level2": "25"
    },
    "Complete Enakhra's Lament": {},
    "Cast Paddewwa Teleport": {
        "Skill1": "Magic",
        "Level1": "54"
    },
    "Have Zahur Make 1,000 Unfinished Potions At Once": {},
    "Complete Room 8 of Pyramid Plunder": {
        "Skill1": "Thieving",
        "Level1": "91"
    },
    "Complete Room 8 of Pyramid Plunder 50 Times": {
        "Skill1": "Thieving",
        "Level1": "91"
    },
    "Complete Room 8 of Pyramid Plunder 100 Times": {
        "Skill1": "Thieving",
        "Level1": "91"
    },
    "Complete Room 8 of Pyramid Plunder 250 Times": {
        "Skill1": "Thieving",
        "Level1": "91"
    },
    "Turn in 100 Summer Sq'irkjuices to Osman": {
        "Skill1": "Thieving",
        "Level1": "65"
    },
    "Smith 1000 Rune Dart Tips": {
        "Skill1": "Smithing",
        "Level1": "89"
    },
    "Defeat the Kalphite Queen": {},
    "Equip a Dragon Chainbody in the Kharidian Desert": {},
    "Cast Blood Barrage": {
        "Skill1": "Magic",
        "Level1": "92"
    },
    "Cast Ice Barrage": {
        "Skill1": "Magic",
        "Level1": "94"
    },
    "Defeat the Kalphite Queen 100 Times": {},
    "Defeat the Kalphite Queen 250 Times": {},
    "Defeat the Kalphite Queen 500 Times": {},
    "Complete the Elite Desert Diary": {
        "Notes": "See diary page"
    },
    "Equip a Full Infinity Robe Set": {
        "Skill1": "Magic",
        "Level1": "50",
        "Skill2": "Defence",
        "Level2": "25"
    },
    "Equip a Master Wand": {
        "Skill1": "Magic",
        "Level1": "60"
    },
    "Craft a Ghorrock Teleport Tablet": {
        "Skill1": "Magic",
        "Level1": "96"
    },
    "Equip a Mage's Book": {
        "Skill1": "Magic",
        "Level1": "60"
    },
    "There are no master tasks for the Kharidian Desert.": {},
    "Craft a Snelm": {
        "Skill1": "Crafting",
        "Level1": "15"
    },
    "Receive a Slayer Task From Mazchna": {},
    "Defeat a Werewolf in Morytania": {},
    "Defeat One of Fenkenstrain's Experiments": {},
    "Defeat a Ghast": {},
    "Complete the Easy Morytania Diary": {
        "Notes": "See diary page"
    },
    "Complete an Easy Temple Trek": {},
    "Visit Port Phasmatys": {},
    "Pet Frank": {},
    "Obtain a Rune Crossbow From a Lucky Impling": {
        "Skill1": "Hunter",
        "Level1": "89"
    },
    "Visit Harmony Island": {},
    "Visit Mos Le'Harmless": {},
    "Complete Floor 1 of the Hallowed Sepulchre": {
        "Skill1": "Agility",
        "Level1": "52"
    },
    "Complete Floor 2 of the Hallowed Sepulchre": {
        "Skill1": "Agility",
        "Level1": "62"
    },
    "Complete the Canifis Agility Course": {
        "Skill1": "Agility",
        "Level1": "40"
    },
    "Complete the Werewolf Agility Course": {
        "Skill1": "Agility",
        "Level1": "60"
    },
    "Catch a Swamp Lizard in Morytania": {
        "Skill1": "Hunter",
        "Level1": "29"
    },
    "Convert 2,000 Daeyalt Shards Into Essence": {
        "Skill1": "Mining",
        "Level1": "60"
    },
    "Craft a Rune Using Daeyalt Essence": {
        "Skill1": "Mining",
        "Level1": "60"
    },
    "Assemble a Slayer Helm": {
        "Skill1": "Crafting",
        "Level1": "55"
    },
    "Loot a Barrows Chest": {},
    "Defeat a Fiyr Shade": {
        "Notes": "Firemaking 65 if killing the shade in Temple Trekking doesn't count"
    },
    "Defeat a Vyrewatch Sentinel": {},
    "Equip a Piece of any Barrows Armour Set": {},
    "Complete the Medium Morytania Diary": {
        "Notes": "See diary page"
    },
    "Complete a Medium Temple Trek": {},
    "Complete Haunted Mine": {},
    "Complete A Taste of Hope": {},
    "Achieve 100% Shades of Mort'Ton Sanctity": {},
    "Equip a Salve Amulet (e)": {},
    "Complete Floor 3 of the Hallowed Sepulchre": {
        "Skill1": "Agility",
        "Level1": "72"
    },
    "Complete Floor 4 of the Hallowed Sepulchre": {
        "Skill1": "Agility",
        "Level1": "82"
    },
    "Complete the Hallowed Sepulchre in 8:00": {
        "Skill1": "Agility",
        "Level1": "92"
    },
    "Purchase a Reward From the Hallowed Sepulchre": {
        "Skill1": "Agility",
        "Level1": "52"
    },
    "Obtain Every Hallowed Tool": {
        "Skill1": "Agility",
        "Level1": "52"
    },
    "Pickpocket a Vyre 50 Times": {
        "Skill1": "Thieving",
        "Level1": "82"
    },
    "Defeat a Gargoyle in Morytania": {
        "Skill1": "Slayer",
        "Level1": "75"
    },
    "Defeat an Abyssal Demon in Morytania": {
        "Skill1": "Slayer",
        "Level1": "85"
    },
    "Defeat the Grotesque Guardians 100 Times": {
        "Skill1": "Slayer",
        "Level1": "75"
    },
    "Equip any Full Barrows Armour Set": {},
    "Equip a Granite Hammer or Granite Ring": {
        "Skill1": "Slayer",
        "Level1": "75"
    },
    "Defeat the Grotesque Guardians": {
        "Skill1": "Slayer",
        "Level1": "75"
    },
    "Complete the Hard Morytania Diary": {
        "Notes": "See diary page"
    },
    "Complete a Hard Temple Trek": {},
    "Complete Sins of the Father": {},
    "Complete Floor 5 of the Hallowed Sepulchre": {
        "Skill1": "Agility",
        "Level1": "92"
    },
    "Complete the Hallowed Sepulchre in 6:30": {
        "Skill1": "Agility",
        "Level1": "92"
    },
    "Equip a Ring of Endurance": {
        "Skill1": "Agility",
        "Level1": "92"
    },
    "Defeat The Nightmare": {},
    "Complete the Theatre of Blood With No Deaths": {},
    "Equip Some Guardian Boots": {
        "Skill1": "Defence",
        "Level1": "75"
    },
    "Equip Every Barrows Armour Set": {
        "Skill1": "Defence",
        "Level1": "70",
        "Skill2": "Magic",
        "Level2": "70",
        "Skill3": "Ranged",
        "Level3": "70",
        "Skill4": "Attack",
        "Level4": "70",
        "Skill5": "Strength",
        "Level5": "70"
    },
    "Equip an Inquisitor's Mace": {
        "Skill1": "Attack",
        "Level1": "75"
    },
    "Equip a Piece of the Inquisitor's Set": {
        "Skill1": "Defence",
        "Level1": "30",
        "Skill2": "Strength",
        "Level2": "70"
    },
    "Equip a Nightmare Staff": {
        "Skill1": "Magic",
        "Level1": "65",
        "Skill2": "Hitpoints",
        "Level2": "50"
    },
    "Create an Amulet of Blood Fury": {
        "Skill1": "Crafting",
        "Level1": "90",
        "Skill2": "Magic",
        "Level2": "87"
    },
    "Equip an Avernic Defender": {
        "Skill1": "Defence",
        "Level1": "70",
        "Skill2": "Attack",
        "Level2": "70"
    },
    "Equip a Sanguinesti Staff": {
        "Skill1": "Magic",
        "Level1": "75"
    },
    "Equip a Scythe of Vitur": {
        "Skill1": "Attack",
        "Level1": "75",
        "Skill2": "Strength",
        "Level2": "75"
    },
    "Equip a Piece of the Justiciar Set": {
        "Skill1": "Defence",
        "Level1": "75"
    },
    "Equip a Ghrazi Rapier": {
        "Skill1": "Attack",
        "Level1": "75"
    },
    "Complete the Theatre of Blood in 20:00": {},
    "Defeat The Nightmare in 3:00": {},
    "Complete the Theatre of Blood 100 Times": {},
    "Complete the Theatre of Blood 200 Times": {},
    "Complete the Theatre of Blood 350 Times": {},
    "Complete the Theatre of Blood 500 Times": {},
    "Defeat the Grotesque Guardians 250 Times": {
        "Skill1": "Slayer",
        "Level1": "75"
    },
    "Complete the Elite Morytania Diary": {
        "Notes": "See diary page"
    },
    "Equip a Full Inquisitor's Set": {
        "Skill1": "Defence",
        "Level1": "30",
        "Skill2": "Strength",
        "Level2": "70"
    },
    "Equip a Nightmare Staff With an Orb": {
        "Skill1": "Magic",
        "Level1": "75",
        "Skill2": "Hitpoints",
        "Level2": "50"
    },
    "Equip a Full Justiciar Set": {
        "Skill1": "Defence",
        "Level1": "75"
    },
    "Complete the Theatre of Blood in 16:00": {},
    "Cook a Rabbit in Tirannwn": {},
    "Harvest some Sweetcorn in Prifddinas": {
        "Skill1": "Farming",
        "Level1": "20"
    },
    "Cross a Trap in Isafdar": {},
    "Defeat a Waterfiend in Tirannwn": {},
    "Defeat a Moss Giant in Tirannwn": {},
    "Use the Bank in Lletya": {},
    "Find Every Memoriam Crystal": {},
    "Charter a Ship From Prifddinas to Port Tyras": {},
    "Talk to Ilfeen in Tirannwn": {},
    "Check a grown Papaya Tree in Lletya": {
        "Skill1": "Farming",
        "Level1": "57"
    },
    "Craft 50 Death Runes": {
        "Skill1": "Runecraft",
        "Level1": "65"
    },
    "Move Your House to Prifddinas": {},
    "Defeat an Elf in Tirannwn": {},
    "Defeat a Bloodveld in Tirannwn": {
        "Skill1": "Slayer",
        "Level1": "50"
    },
    "Defeat a Kurask in Tirannwn": {
        "Skill1": "Slayer",
        "Level1": "70"
    },
    "Use an Elven Teleport Crystal": {},
    "Check a grown Crystal Tree": {
        "Skill1": "Farming",
        "Level1": "74"
    },
    "Catch a Crystal Impling": {
        "Skill1": "Hunter",
        "Level1": "80"
    },
    "Complete the Prifddinas Agility Course": {
        "Skill1": "Agility",
        "Level1": "75"
    },
    "Complete the Prifddinas Agility Course in 1:10": {
        "Skill1": "Agility",
        "Level1": "75"
    },
    "Pickpocket an Elf 50 Times": {
        "Skill1": "Thieving",
        "Level1": "85"
    },
    "Craft a Piece of Crystal Armour": {
        "Skill1": "Smithing",
        "Level1": "70",
        "Skill2": "Crafting",
        "Level2": "50"
    },
    "Complete the Gauntlet": {},
    "Defeat Zalcano": {},
    "Defeat Zulrah": {},
    "Defeat a Dark Beast in Tirannwn": {
        "Skill1": "Slayer",
        "Level1": "90"
    },
    "Equip a Dark Bow": {
        "Skill1": "Ranged",
        "Level1": "60"
    },
    "Defeat Zulrah in 1:30": {},
    "Complete the Gauntlet in 8:00": {},
    "Equip a Crystal Bow": {
        "Skill1": "Ranged",
        "Level1": "70",
        "Skill2": "Agility",
        "Level2": "50"
    },
    "Equip a Crystal Shield": {
        "Skill1": "Defence",
        "Level1": "70",
        "Skill2": "Agility",
        "Level2": "50"
    },
    "Equip a Crystal Halberd": {
        "Skill1": "Attack",
        "Level1": "70",
        "Skill2": "Agility",
        "Level2": "50",
        "Skill3": "Strength",
        "Level3": "35"
    },
    "Defeat a Nechryael in Tirannwn": {
        "Skill1": "Slayer"
    },
    "Craft an Eternal Teleport Crystal": {
        "Skill1": "Smithing",
        "Level1": "80",
        "Skill2": "Crafting",
        "Level2": "80"
    },
    "Open the Enhanced Crystal Chest": {
        "Skill1": "Smithing",
        "Level1": "80",
        "Skill2": "Crafting",
        "Level2": "80"
    },
    "Dissect 50 Sacred Eels": {
        "Skill1": "Fishing",
        "Level1": "87"
    },
    "Equip an Elven Signet": {
        "Skill1": "Hunter",
        "Level1": "80"
    },
    "Obtain a Zalcano Shard": {},
    "Equip a Full Crystal Armour Set": {
        "Skill1": "Smithing",
        "Level1": "74",
        "Skill2": "Crafting",
        "Level2": "74"
    },
    "Complete the Corrupted Gauntlet": {},
    "Obtain a Crystal Tool Seed": {},
    "Equip a Serpentine Helm": {},
    "Craft a Toxic Blowpipe": {},
    "Craft a Toxic Trident": {},
    "Defeat Zulrah in 0:54": {},
    "Complete the Gauntlet in 5:00": {},
    "Complete the Corrupted Gauntlet in 8:30": {},
    "Complete the Corrupted Gauntlet in 7:00": {},
    "Complete the Corrupted Gauntlet 100 Times": {},
    "Complete the Corrupted Gauntlet 250 Times": {},
    "Defeat Zalcano 250 Times": {},
    "Defeat Zalcano 500 Times": {},
    "Defeat Zulrah 250 Times": {},
    "Defeat Zulrah 500 Times": {},
    "Equip a Piece of the Dragonstone Armour Set": {},
    "Equip a Corrupted Blade of Saeldor": {},
    "Defeat Zulrah in 0:42": {},
    "Complete the Corrupted Gauntlet in 5:00": {},
    "Equip a Crystal Crown": {},
    "Sacrifice Some Bones at the Chaos Temple": {},
    "Use the Abyss": {},
    "Defeat a Lava Dragon in the Wilderness": {},
    "Defeat a Fire Giant in the Wilderness": {},
    "Defeat a Chaos Dwarf in the Wilderness": {},
    "Defeat a Green Dragon in the Wilderness": {},
    "Complete the Easy Wilderness Diary": {
        "Notes": "See diary page"
    },
    "Order a Drink at the Old Nite": {},
    "Use a Lever to Teleport to Edgeville": {},
    "Pray at the Southern Chaos Temple": {},
    "Pray at the Western Chaos Temple": {},
    "Enter the Wilderness Resource Area": {},
    "Enter the Wilderness God Wars Dungeon": {},
    "Use the Bank at the Mage Arena": {},
    "Visit Ferox Enclave": {},
    "Sacrifice Some Dragon Bones at the Chaos Temple": {},
    "Bury Some Lava Dragon Bones": {},
    "Complete the Wilderness Agility Course": {
        "Skill1": "Agility",
        "Level1": "52"
    },
    "Catch a Black Salamander": {
        "Skill1": "Hunter",
        "Level1": "67"
    },
    "Fill a Large Pouch": {
        "Skill1": "Runecraft",
        "Level1": "50"
    },
    "Defeat the Crazy Archaeologist": {},
    "Defeat Scorpia": {},
    "Defeat the Chaos Fanatic": {},
    "Defeat the Chaos Elemental": {},
    "Equip a Fedora": {},
    "Obtain an Ecumenical Key": {},
    "Equip a Lava Battlestaff": {},
    "Equip a Bracelet of Ethereum": {},
    "Equip a God Cape": {},
    "Cast Saradomin Strike": {},
    "Cast Claws of Guthix": {},
    "Cast Flames of Zamorak": {},
    "Complete the Medium Wilderness Diary": {
        "Notes": "See diary page"
    },
    "Open a Looting Bag": {},
    "Enter the Deep Wilderness Dungeon": {},
    "Open One of Larran's Chests": {},
    "Catch 100 Dark Crabs": {
        "Skill1": "Fishing",
        "Level1": "85"
    },
    "Catch a Black Chinchompa": {
        "Skill1": "Hunter",
        "Level1": "73"
    },
    "Craft an Air Battlestaff in the Wilderness": {
        "Skill1": "Crafting",
        "Level1": "66"
    },
    "Fill a Giant Pouch": {
        "Skill1": "Runecraft",
        "Level1": "75"
    },
    "Defeat Venenatis": {},
    "Defeat Callisto": {},
    "Defeat Vet'ion": {},
    "Defeat the King Black Dragon": {},
    "Equip a Dragon Pickaxe": {},
    "Equip a Dragon 2H Sword in the Wilderness": {},
    "Equip an Enchanted Slayer Staff": {},
    "Trade With the Emblem Trader": {},
    "Imbue a God Cape": {},
    "Complete the Hard Wilderness Diary": {
        "Notes": "See diary page"
    },
    "Equip a Piece of the Dagon'Hai Set": {
        "Skill1": "Magic",
        "Level1": "70",
        "Skill2": "Defence",
        "Level2": "40"
    },
    "Cook a Dark Crab": {
        "Skill1": "Cooking",
        "Level1": "90"
    },
    "Make an Extended Antifire Potion": {
        "Skill1": "Herblore",
        "Level1": "84"
    },
    "Equip 250 Black Chinchompas": {
        "Skill1": "Hunter",
        "Level1": "73"
    },
    "Equip 500 Black Chinchompas": {
        "Skill1": "Hunter",
        "Level1": "73"
    },
    "Equip 1000 Black Chinchompas": {
        "Skill1": "Hunter",
        "Level1": "73"
    },
    "Mine Some Runite Ore in the Wilderness": {
        "Skill1": "Mining",
        "Level1": "85"
    },
    "Equip a Treasonous Ring": {},
    "Equip a Tyrannical Ring": {},
    "Equip a Ring of the Gods": {},
    "Equip a Craw's Bow": {
        "Skill1": "Ranged",
        "Level1": "60"
    },
    "Equip a Viggora's Chainmace": {
        "Skill1": "Attack",
        "Level1": "60"
    },
    "Equip a Thammaron's Sceptre": {
        "Skill1": "Magic",
        "Level1": "60"
    },
    "Defeat the Corporeal Beast": {},
    "Defeat the Corporeal Beast 100 Times": {},
    "Defeat the Corporeal Beast 250 Times": {},
    "Defeat the Corporeal Beast 500 Times": {},
    "Equip a Blessed Spirit Shield": {
        "Skill1": "Defence",
        "Level1": "70",
        "Skill2": "Prayer",
        "Level2": "60"
    },
    "Equip a Malediction Ward": {
        "Skill1": "Defence",
        "Level1": "60"
    },
    "Equip an Odium Ward": {
        "Skill1": "Defence",
        "Level1": "60"
    },
    "Build an Obelisk": {
        "Skill1": "Construction",
        "Level1": "80"
    },
    "Complete the Elite Wilderness Diary": {
        "Notes": "See diary page"
    },
    "Equip a Full Dagon'Hai Set": {
        "Skill1": "Magic",
        "Level1": "70",
        "Skill2": "Defence",
        "Level2": "40"
    },
    "Equip a Spectral or Arcane Spirit Shield": {
        "Skill1": "Defence",
        "Level1": "75",
        "Skill2": "Prayer",
        "Level2": "70",
        "Skill3": "Magic",
        "Level3": "65"
    },
    "Equip an Elysian Spirit Shield": {
        "Skill1": "Defence",
        "Level1": "75",
        "Skill2": "Prayer",
        "Level2": "75"
    },
    "Obtain Every Revenant Weapon": {},
    "Equip an Amulet of Eternal Glory": {}
}